{
	"completely_empty": false,
	"image": {
		"height": 990,
		"scale": 0.9575757575757575,
		"width": 1332
	},
	"mark": [
		{
			"class_idx": 0,
			"name": "number_plate",
			"points": [
				{
					"int_x": 1111,
					"int_y": 547,
					"x": 0.833933933933934,
					"y": 0.5525252525252525
				},
				{
					"int_x": 1311,
					"int_y": 547,
					"x": 0.9840840840840841,
					"y": 0.5525252525252525
				},
				{
					"int_x": 1311,
					"int_y": 590,
					"x": 0.9840840840840841,
					"y": 0.5957575757575758
				},
				{
					"int_x": 1111,
					"int_y": 590,
					"x": 0.833933933933934,
					"y": 0.5957575757575758
				}
			],
			"rect": {
				"h": 0.04323232323232329,
				"int_h": 44,
				"int_w": 201,
				"int_x": 1111,
				"int_y": 547,
				"w": 0.1501501501501501,
				"x": 0.833933933933934,
				"y": 0.5525252525252525
			}
		},
		{
			"class_idx": 33,
			"name": "W",
			"points": [
				{
					"int_x": 1136,
					"int_y": 550,
					"x": 0.8530780780780781,
					"y": 0.5557575757575758
				},
				{
					"int_x": 1158,
					"int_y": 550,
					"x": 0.8691441441441442,
					"y": 0.5557575757575758
				},
				{
					"int_x": 1158,
					"int_y": 588,
					"x": 0.8691441441441442,
					"y": 0.5937373737373738
				},
				{
					"int_x": 1136,
					"int_y": 588,
					"x": 0.8530780780780781,
					"y": 0.5937373737373738
				}
			],
			"rect": {
				"h": 0.037979797979798,
				"int_h": 39,
				"int_w": 23,
				"int_x": 1136,
				"int_y": 550,
				"w": 0.016066066066066087,
				"x": 0.8530780780780781,
				"y": 0.5557575757575758
			}
		},
		{
			"class_idx": 31,
			"name": "U",
			"points": [
				{
					"int_x": 1160,
					"int_y": 550,
					"x": 0.8711711711711713,
					"y": 0.5554545454545455
				},
				{
					"int_x": 1181,
					"int_y": 550,
					"x": 0.8867867867867868,
					"y": 0.5554545454545455
				},
				{
					"int_x": 1181,
					"int_y": 588,
					"x": 0.8867867867867868,
					"y": 0.594040404040404
				},
				{
					"int_x": 1160,
					"int_y": 588,
					"x": 0.8711711711711713,
					"y": 0.594040404040404
				}
			],
			"rect": {
				"h": 0.0385858585858585,
				"int_h": 39,
				"int_w": 22,
				"int_x": 1160,
				"int_y": 550,
				"w": 0.01561561561561553,
				"x": 0.8711711711711713,
				"y": 0.5554545454545455
			}
		},
		{
			"class_idx": 1,
			"name": "0",
			"points": [
				{
					"int_x": 1194,
					"int_y": 550,
					"x": 0.8963213213213213,
					"y": 0.5557575757575758
				},
				{
					"int_x": 1214,
					"int_y": 550,
					"x": 0.9114864864864864,
					"y": 0.5557575757575758
				},
				{
					"int_x": 1214,
					"int_y": 589,
					"x": 0.9114864864864864,
					"y": 0.594949494949495
				},
				{
					"int_x": 1194,
					"int_y": 589,
					"x": 0.8963213213213213,
					"y": 0.594949494949495
				}
			],
			"rect": {
				"h": 0.03919191919191922,
				"int_h": 40,
				"int_w": 21,
				"int_x": 1194,
				"int_y": 550,
				"w": 0.015165165165165195,
				"x": 0.8963213213213213,
				"y": 0.5557575757575758
			}
		},
		{
			"class_idx": 10,
			"name": "9",
			"points": [
				{
					"int_x": 1217,
					"int_y": 551,
					"x": 0.9138138138138138,
					"y": 0.5565656565656566
				},
				{
					"int_x": 1235,
					"int_y": 551,
					"x": 0.9273273273273274,
					"y": 0.5565656565656566
				},
				{
					"int_x": 1235,
					"int_y": 589,
					"x": 0.9273273273273274,
					"y": 0.594949494949495
				},
				{
					"int_x": 1217,
					"int_y": 589,
					"x": 0.9138138138138138,
					"y": 0.594949494949495
				}
			],
			"rect": {
				"h": 0.03838383838383841,
				"int_h": 39,
				"int_w": 19,
				"int_x": 1217,
				"int_y": 551,
				"w": 0.013513513513513598,
				"x": 0.9138138138138138,
				"y": 0.5565656565656566
			}
		},
		{
			"class_idx": 9,
			"name": "8",
			"points": [
				{
					"int_x": 1238,
					"int_y": 550,
					"x": 0.9291291291291291,
					"y": 0.5555555555555556
				},
				{
					"int_x": 1257,
					"int_y": 550,
					"x": 0.9438438438438438,
					"y": 0.5555555555555556
				},
				{
					"int_x": 1257,
					"int_y": 589,
					"x": 0.9438438438438438,
					"y": 0.5947474747474748
				},
				{
					"int_x": 1238,
					"int_y": 589,
					"x": 0.9291291291291291,
					"y": 0.5947474747474748
				}
			],
			"rect": {
				"h": 0.03919191919191922,
				"int_h": 40,
				"int_w": 20,
				"int_x": 1238,
				"int_y": 550,
				"w": 0.014714714714714638,
				"x": 0.9291291291291291,
				"y": 0.5555555555555556
			}
		},
		{
			"class_idx": 7,
			"name": "6",
			"points": [
				{
					"int_x": 1258,
					"int_y": 548,
					"x": 0.9446696696696696,
					"y": 0.5535353535353535
				},
				{
					"int_x": 1279,
					"int_y": 548,
					"x": 0.9601351351351352,
					"y": 0.5535353535353535
				},
				{
					"int_x": 1279,
					"int_y": 587,
					"x": 0.9601351351351352,
					"y": 0.5931313131313132
				},
				{
					"int_x": 1258,
					"int_y": 587,
					"x": 0.9446696696696696,
					"y": 0.5931313131313132
				}
			],
			"rect": {
				"h": 0.03959595959595963,
				"int_h": 40,
				"int_w": 22,
				"int_x": 1258,
				"int_y": 548,
				"w": 0.015465465465465567,
				"x": 0.9446696696696696,
				"y": 0.5535353535353535
			}
		},
		{
			"class_idx": 18,
			"name": "H",
			"points": [
				{
					"int_x": 1281,
					"int_y": 550,
					"x": 0.9613363363363363,
					"y": 0.5554545454545455
				},
				{
					"int_x": 1301,
					"int_y": 550,
					"x": 0.9768018018018019,
					"y": 0.5554545454545455
				},
				{
					"int_x": 1301,
					"int_y": 587,
					"x": 0.9768018018018019,
					"y": 0.5924242424242424
				},
				{
					"int_x": 1281,
					"int_y": 587,
					"x": 0.9613363363363363,
					"y": 0.5924242424242424
				}
			],
			"rect": {
				"h": 0.036969696969696875,
				"int_h": 38,
				"int_w": 21,
				"int_x": 1281,
				"int_y": 550,
				"w": 0.015465465465465567,
				"x": 0.9613363363363363,
				"y": 0.5554545454545455
			}
		}
	],
	"timestamp": 1661449100,
	"version": "1.7.5-1"
}
